mhctools/__init__.py
mhctools/base_commandline_predictor.py
mhctools/base_predictor.py
mhctools/binding_prediction.py
mhctools/binding_prediction_collection.py
mhctools/cleanup_context.py
mhctools/common.py
mhctools/iedb.py
mhctools/input_file_formats.py
mhctools/logging.conf
mhctools/logging.py
mhctools/mhcflurry.py
mhctools/mixmhcpred.py
mhctools/netchop.py
mhctools/netmhc.py
mhctools/netmhc3.py
mhctools/netmhc4.py
mhctools/netmhc_cons.py
mhctools/netmhc_pan.py
mhctools/netmhc_pan28.py
mhctools/netmhc_pan3.py
mhctools/netmhc_pan4.py
mhctools/netmhc_pan41.py
mhctools/netmhcii_pan.py
mhctools/parsing.py
mhctools/process_helpers.py
mhctools/random_predictor.py
mhctools/unsupported_allele.py
mhctools/cli/__init__.py
mhctools/cli/args.py
mhctools/cli/parsing_helpers.py
mhctools/cli/script.py
mhctools-1.9.0.dist-info/LICENSE
mhctools-1.9.0.dist-info/METADATA
mhctools-1.9.0.dist-info/WHEEL
mhctools-1.9.0.dist-info/entry_points.txt
mhctools-1.9.0.dist-info/top_level.txt
mhctools-1.9.0.dist-info/RECORD
