Metadata-Version: 2.1
Name: mhctools
Version: 1.9.0
Summary: Python interface to running command-line and web-based MHC binding predictors
Home-page: https://github.com/openvax/mhctools
Author: Alex Rubinsteyn, Julia Kodysh, Tim O'Donnell
Author-email: alex@openvax.org, julia@openvax.org, tim@openvax.org
License: http://www.apache.org/licenses/LICENSE-2.0.html
Classifier: Development Status :: 4 - Beta
Classifier: Environment :: Console
Classifier: Operating System :: OS Independent
Classifier: Intended Audience :: Science/Research
Classifier: License :: OSI Approved :: Apache Software License
Classifier: Programming Language :: Python
Classifier: Topic :: Scientific/Engineering :: Bio-Informatics
License-File: LICENSE
Requires-Dist: numpy >=1.7
Requires-Dist: pandas >=0.13.1
Requires-Dist: varcode >=0.5.9
Requires-Dist: pyensembl >=1.0.3
Requires-Dist: sercol >=0.0.2
Requires-Dist: mhcflurry >=2.0.0
Requires-Dist: mhcnames >=0.3.2
